week 1/branch_comp.v
module branch_comp(
    input wire [31:0] a,
    input wire [31:0] b,
    input wire [2:0] funct3,
    output reg branch_taken
);
always @(*) begin
    case (funct3)
        3'b000: branch_taken = (a == b);               // BEQ
        3'b001: branch_taken = (a != b);               // BNE
        3'b100: branch_taken = ($signed(a) < $signed(b));  // BLT
        3'b101: branch_taken = ($signed(a) >= $signed(b)); // BGE
        default: branch_taken = 0;
    endcase
end
endmodule

week 1/alu.v
module alu(
    input wire [31:0] a,
    input wire [31:0] b,
    input wire [3:0] alu_ctrl,
    output reg [31:0] result,
    output wire zero
);

assign zero = (result == 0);

always @(*) begin
    case(alu_ctrl)
        4'b0000: result = a + b;
        4'b0001: result = a - b;
        4'b0010: result = a & b;
        4'b0011: result = a | b;
        4'b0100: result = a ^ b;
        4'b0101: result = ($signed(a) < $signed(b)) ? 1 : 0;
        default: result = 0;
    endcase
end

endmodule

week 3/alu_control.v
module alu_control(
    input wire [2:0] funct3,
    input wire [6:0] funct7,
    input wire [6:0] opcode,
    output reg [3:0] alu_ctrl
);
always @(*) begin
    case (opcode)
        7'b0110011: begin // R-type
            case ({funct7, funct3})
                {7'b0000000, 3'b000}: alu_ctrl = 4'b0000; // ADD
                {7'b0100000, 3'b000}: alu_ctrl = 4'b0001; // SUB
                {7'b0000000, 3'b111}: alu_ctrl = 4'b0010; // AND
                {7'b0000000, 3'b110}: alu_ctrl = 4'b0011; // OR
                {7'b0000000, 3'b100}: alu_ctrl = 4'b0100; // XOR
                {7'b0000000, 3'b010}: alu_ctrl = 4'b0101; // SLT
                default: alu_ctrl = 4'b1111;
            endcase
        end
        default: alu_ctrl = 4'b1111;
    endcase
end
endmodule

week 1/decoder.v
module decoder(
    input wire [31:0] instr,
    output wire [6:0] opcode,
    output wire [4:0] rd,
    output wire [2:0] funct3,
    output wire [4:0] rs1,
    output wire [4:0] rs2,
    output wire [6:0] funct7
);
assign opcode = instr[6:0];
assign rd     = instr[11:7];
assign funct3 = instr[14:12];
assign rs1    = instr[19:15];
assign rs2    = instr[24:20];
assign funct7 = instr[31:25];
endmodule

week 1/instr_mem.v
module instr_mem(
    input wire [31:0] addr,
    output wire [31:0] instr
);
reg [31:0] mem [0:255];
initial begin
    $readmemh("program.hex", mem);
end
assign instr = mem[addr[9:2]]; // word‑aligned
endmodule

week 1/pc.v
module pc(
    input wire clk,
    input wire reset,
    input wire [31:0] pc_next,
    output reg [31:0] pc_out
);
always @(posedge clk or posedge reset) begin
    if (reset)
        pc_out <= 0;
    else
        pc_out <= pc_next;
end
endmodule

week 1/top_week3.v
module top_week3(
    input wire clk,
    input wire reset
);
wire [31:0] pc_out, pc_next, instr;
wire [6:0] opcode;
wire [4:0] rd, rs1, rs2;
wire [2:0] funct3;
wire [6:0] funct7;
wire [3:0] alu_ctrl;
wire [31:0] alu_result;
wire branch_taken;

assign pc_next = branch_taken ? pc_out + 4 : pc_out + 4;

pc PC(clk, reset, pc_next, pc_out);
instr_mem IM(pc_out, instr);
decoder DEC(instr, opcode, rd, funct3, rs1, rs2, funct7);
alu_control AC(funct3, funct7, opcode, alu_ctrl);
alu ALU(32'd10, 32'd5, alu_ctrl, alu_result, ); // example operands
branch_comp BC(32'd10, 32'd5, funct3, branch_taken);
endmodule

week 1/tb_top_week3.v
`timescale 1ns/1ps

module tb_top_week3;

    reg clk;
    reg reset;

    // Instantiate the top module
    top_week3 uut (
        .clk(clk),
        .reset(reset)
    );

    // Clock generation
    always #5 clk = ~clk;

    initial begin
        // Dumpfile setup
        $dumpfile("top_week3.vcd");
        $dumpvars(0, tb_top_week3);

        // Initialize
        clk = 0;
        reset = 1;

        // Release reset
        #10 reset = 0;

        // Run simulation
        #200 $finish;
    end

endmodule

week 1/top_week3.vcd
$date
	Sat Jun 20 15:38:25 2026
$end
$version
	Icarus Verilog
$end
$timescale
	1ps
$end
$scope module tb_top_week3 $end
$var reg 1 ! clk $end
$var reg 1 " reset $end
$scope module uut $end
$var wire 1 ! clk $end
$var wire 1 " reset $end
$var wire 5 # rs2 [4:0] $end
$var wire 5 $ rs1 [4:0] $end
$var wire 5 % rd [4:0] $end
$var wire 32 & pc_out [31:0] $end
$var wire 32 ' pc_next [31:0] $end
$var wire 7 ( opcode [6:0] $end
$var wire 32 ) instr [31:0] $end
$var wire 7 * funct7 [6:0] $end
$var wire 3 + funct3 [2:0] $end
$var wire 1 , branch_taken $end
$var wire 32 - alu_result [31:0] $end
$var wire 4 . alu_ctrl [3:0] $end
$scope module AC $end
$var wire 7 / opcode [6:0] $end
$var wire 7 0 funct7 [6:0] $end
$var wire 3 1 funct3 [2:0] $end
$var reg 4 2 alu_ctrl [3:0] $end
$upscope $end
$scope module ALU $end
$var wire 32 3 a [31:0] $end
$var wire 4 4 alu_ctrl [3:0] $end
$var wire 32 5 b [31:0] $end
$var wire 1 6 zero $end
$var reg 32 7 result [31:0] $end
$upscope $end
$scope module BC $end
$var wire 32 8 a [31:0] $end
$var wire 32 9 b [31:0] $end
$var wire 3 : funct3 [2:0] $end
$var reg 1 , branch_taken $end
$upscope $end
$scope module DEC $end
$var wire 5 ; rs2 [4:0] $end
$var wire 5 < rs1 [4:0] $end
$var wire 5 = rd [4:0] $end
$var wire 7 > opcode [6:0] $end
$var wire 32 ? instr [31:0] $end
$var wire 7 @ funct7 [6:0] $end
$var wire 3 A funct3 [2:0] $end
$upscope $end
$scope module IM $end
$var wire 32 B instr [31:0] $end
$var wire 32 C addr [31:0] $end
$upscope $end
$scope module PC $end
$var wire 1 ! clk $end
$var wire 32 D pc_next [31:0] $end
$var wire 1 " reset $end
$var reg 32 E pc_out [31:0] $end
$upscope $end
$upscope $end
$upscope $end
$enddefinitions $end
$comment Show the parameter values. $end
$dumpall
$end
#0
$dumpvars
b0 E
b100 D
b0 C
b110011 B
b0 A
b0 @
b110011 ?
b110011 >
b0 =
b0 <
b0 ;
b0 :
b101 9
b1010 8
b1111 7
06
b101 5
b0 4
b1010 3
b0 2
b0 1
b0 0
b110011 /
b0 .
b1111 -
0,
b0 +
b0 *
b110011 )
b110011 (
b100 '
b0 &
b0 %
b0 $
b0 #
1"
0!
$end
#5000
1!
#10000
0!
0"
#15000
b10 #
b10 ;
b1 $
b1 <
b11 %
b11 =
b1000001000000110110011 )
b1000001000000110110011 ?
b1000001000000110110011 B
b1000 '
b1000 D
b100 &
b100 C
b100 E
1!
#20000
0!
#25000
b11 #
b11 ;
b10 $
b10 <
b100 %
b100 =
b1100010000001000110011 )
b1100010000001000110011 ?
b1100010000001000110011 B
b1100 '
b1100 D
b1000 &
b1000 C
b1000 E
1!
#30000
0!
#35000
16
b0 -
b0 7
b1111 .
b1111 2
b1111 4
bx *
bx 0
bx @
bx #
bx ;
bx $
bx <
bx +
bx 1
bx :
bx A
bx %
bx =
bx (
bx /
bx >
bx )
bx ?
bx B
b10000 '
b10000 D
b1100 &
b1100 C
b1100 E
1!
#40000
0!
#45000
b10100 '
b10100 D
b10000 &
b10000 C
b10000 E
1!
#50000
0!
#55000
b11000 '
b11000 D
b10100 &
b10100 C
b10100 E
1!
#60000
0!
#65000
b11100 '
b11100 D
b11000 &
b11000 C
b11000 E
1!
#70000
0!
#75000
b100000 '
b100000 D
b11100 &
b11100 C
b11100 E
1!
#80000
0!
#85000
b100100 '
b100100 D
b100000 &
b100000 C
b100000 E
1!
#90000
0!
#95000
b101000 '
b101000 D
b100100 &
b100100 C
b100100 E
1!
#100000
0!
#105000
b101100 '
b101100 D
b101000 &
b101000 C
b101000 E
1!
#110000
0!
#115000
b110000 '
b110000 D
b101100 &
b101100 C
b101100 E
1!
#120000
0!
#125000
b110100 '
b110100 D
b110000 &
b110000 C
b110000 E
1!
#130000
0!
#135000
b111000 '
b111000 D
b110100 &
b110100 C
b110100 E
1!
#140000
0!
#145000
b111100 '
b111100 D
b111000 &
b111000 C
b111000 E
1!
#150000
0!
#155000
b1000000 '
b1000000 D
b111100 &
b111100 C
b111100 E
1!
#160000
0!
#165000
b1000100 '
b1000100 D
b1000000 &
b1000000 C
b1000000 E
1!
#170000
0!
#175000
b1001000 '
b1001000 D
b1000100 &
b1000100 C
b1000100 E
1!
#180000
0!
#185000
b1001100 '
b1001100 D
b1001000 &
b1001000 C
b1001000 E
1!
#190000
0!
#195000
b1010000 '
b1010000 D
b1001100 &
b1001100 C
b1001100 E
1!
#200000
0!
#205000
b1010100 '
b1010100 D
b1010000 &
b1010000 C
b1010000 E
1!
