week 4/writeback_mux.v
module writeback_mux(
    input wire [31:0] alu_result,
    input wire [31:0] mem_data,
    input wire mem_to_reg,
    output wire [31:0] wb_data
);
assign wb_data = mem_to_reg ? mem_data : alu_result;
endmodule

week 1/data_mem.v
module data_mem(
    input wire clk,
    input wire mem_read,
    input wire mem_write,
    input wire [31:0] addr,
    input wire [31:0] write_data,
    output reg [31:0] read_data
);
reg [31:0] mem [0:255];

always @(posedge clk) begin
    if (mem_write)
        mem[addr[9:2]] <= write_data;
end

always @(*) begin
    if (mem_read)
        read_data = mem[addr[9:2]];
    else
        read_data = 32'b0;
end
endmodule

week 1/alu.v
module alu(
    input wire [31:0] a,
    input wire [31:0] b,
    input wire [3:0] alu_ctrl,
    output reg [31:0] result,
    output wire zero
);

assign zero = (result == 0);

always @(*) begin
    case(alu_ctrl)
        4'b0000: result = a + b;
        4'b0001: result = a - b;
        4'b0010: result = a & b;
        4'b0011: result = a | b;
        4'b0100: result = a ^ b;
        4'b0101: result = ($signed(a) < $signed(b)) ? 1 : 0;
        default: result = 0;
    endcase
end

endmodule

week 3/alu_control.v
module alu_control(
    input wire [2:0] funct3,
    input wire [6:0] funct7,
    input wire [6:0] opcode,
    output reg [3:0] alu_ctrl
);
always @(*) begin
    case (opcode)
        7'b0110011: begin // R-type
            case ({funct7, funct3})
                {7'b0000000, 3'b000}: alu_ctrl = 4'b0000; // ADD
                {7'b0100000, 3'b000}: alu_ctrl = 4'b0001; // SUB
                {7'b0000000, 3'b111}: alu_ctrl = 4'b0010; // AND
                {7'b0000000, 3'b110}: alu_ctrl = 4'b0011; // OR
                {7'b0000000, 3'b100}: alu_ctrl = 4'b0100; // XOR
                {7'b0000000, 3'b010}: alu_ctrl = 4'b0101; // SLT
                default: alu_ctrl = 4'b1111;
            endcase
        end
        default: alu_ctrl = 4'b1111;
    endcase
end
endmodule

week 1/decoder.v
module decoder(
    input wire [31:0] instr,
    output wire [6:0] opcode,
    output wire [4:0] rd,
    output wire [2:0] funct3,
    output wire [4:0] rs1,
    output wire [4:0] rs2,
    output wire [6:0] funct7
);
assign opcode = instr[6:0];
assign rd     = instr[11:7];
assign funct3 = instr[14:12];
assign rs1    = instr[19:15];
assign rs2    = instr[24:20];
assign funct7 = instr[31:25];
endmodule

week 1/instr_mem.v
module instr_mem(
    input wire [31:0] addr,
    output wire [31:0] instr
);
reg [31:0] mem [0:255];
initial begin
    $readmemh("program.hex", mem);
end
assign instr = mem[addr[9:2]]; // word‑aligned
endmodule

week 1/pc.v
module pc(
    input wire clk,
    input wire reset,
    input wire [31:0] pc_next,
    output reg [31:0] pc_out
);
always @(posedge clk or posedge reset) begin
    if (reset)
        pc_out <= 0;
    else
        pc_out <= pc_next;
end
endmodule

week 1/top_week4.v
module top_week4(
    input wire clk,
    input wire reset
);
wire [31:0] pc_out, pc_next, instr;
wire [6:0] opcode;
wire [4:0] rd, rs1, rs2;
wire [2:0] funct3;
wire [6:0] funct7;
wire [3:0] alu_ctrl;
wire [31:0] alu_result, mem_data, wb_data;
wire mem_read, mem_write, mem_to_reg, reg_write;

assign pc_next = pc_out + 4;

pc PC(clk, reset, pc_next, pc_out);
instr_mem IM(pc_out, instr);
decoder DEC(instr, opcode, rd, funct3, rs1, rs2, funct7);
alu_control AC(funct3, funct7, opcode, alu_ctrl);
alu ALU(32'd10, 32'd5, alu_ctrl, alu_result, );
data_mem DM(clk, mem_read, mem_write, alu_result, 32'hA5A5A5A5, mem_data);
writeback_mux WB(alu_result, mem_data, mem_to_reg, wb_data);
endmodule

week 4/tb_top_week4.v
`timescale 1ns/1ps
module tb_top_week4;
reg clk, reset;
top_week4 uut(clk, reset);

initial begin
    $dumpfile("top_week4.vcd");
    $dumpvars(0, tb_top_week4);
    clk = 0; reset = 1;
    #10 reset = 0;
    #200 $finish;
end

always #5 clk = ~clk;
endmodule

week 1/top_week4.vcd
$date
	Sat Jun 20 15:52:35 2026
$end
$version
	Icarus Verilog
$end
$timescale
	1ps
$end
$scope module tb_top_week4 $end
$var reg 1 ! clk $end
$var reg 1 " reset $end
$scope module uut $end
$var wire 1 ! clk $end
$var wire 1 # mem_read $end
$var wire 1 $ mem_to_reg $end
$var wire 1 % mem_write $end
$var wire 1 " reset $end
$var wire 32 & wb_data [31:0] $end
$var wire 5 ' rs2 [4:0] $end
$var wire 5 ( rs1 [4:0] $end
$var wire 5 ) rd [4:0] $end
$var wire 32 * pc_out [31:0] $end
$var wire 32 + pc_next [31:0] $end
$var wire 7 , opcode [6:0] $end
$var wire 32 - mem_data [31:0] $end
$var wire 32 . instr [31:0] $end
$var wire 7 / funct7 [6:0] $end
$var wire 3 0 funct3 [2:0] $end
$var wire 32 1 alu_result [31:0] $end
$var wire 4 2 alu_ctrl [3:0] $end
$scope module AC $end
$var wire 7 3 opcode [6:0] $end
$var wire 7 4 funct7 [6:0] $end
$var wire 3 5 funct3 [2:0] $end
$var reg 4 6 alu_ctrl [3:0] $end
$upscope $end
$scope module ALU $end
$var wire 32 7 a [31:0] $end
$var wire 4 8 alu_ctrl [3:0] $end
$var wire 32 9 b [31:0] $end
$var wire 1 : zero $end
$var reg 32 ; result [31:0] $end
$upscope $end
$scope module DEC $end
$var wire 5 < rs2 [4:0] $end
$var wire 5 = rs1 [4:0] $end
$var wire 5 > rd [4:0] $end
$var wire 7 ? opcode [6:0] $end
$var wire 32 @ instr [31:0] $end
$var wire 7 A funct7 [6:0] $end
$var wire 3 B funct3 [2:0] $end
$upscope $end
$scope module DM $end
$var wire 32 C addr [31:0] $end
$var wire 1 ! clk $end
$var wire 1 # mem_read $end
$var wire 1 % mem_write $end
$var wire 32 D write_data [31:0] $end
$var reg 32 E read_data [31:0] $end
$upscope $end
$scope module IM $end
$var wire 32 F instr [31:0] $end
$var wire 32 G addr [31:0] $end
$upscope $end
$scope module PC $end
$var wire 1 ! clk $end
$var wire 32 H pc_next [31:0] $end
$var wire 1 " reset $end
$var reg 32 I pc_out [31:0] $end
$upscope $end
$scope module WB $end
$var wire 32 J alu_result [31:0] $end
$var wire 32 K mem_data [31:0] $end
$var wire 1 $ mem_to_reg $end
$var wire 32 L wb_data [31:0] $end
$upscope $end
$upscope $end
$upscope $end
$enddefinitions $end
$comment Show the parameter values. $end
$dumpall
$end
#0
$dumpvars
b0xxxx L
b0 K
b1111 J
b0 I
b100 H
b0 G
b110011 F
b0 E
b10100101101001011010010110100101 D
b1111 C
b0 B
b0 A
b110011 @
b110011 ?
b0 >
b0 =
b0 <
b1111 ;
0:
b101 9
b0 8
b1010 7
b0 6
b0 5
b0 4
b110011 3
b0 2
b1111 1
b0 0
b0 /
b110011 .
b0 -
b110011 ,
b100 +
b0 *
b0 )
b0 (
b0 '
b0xxxx &
z%
z$
z#
1"
0!
$end
#5000
1!
#10000
0!
0"
#15000
b10 '
b10 <
b1 (
b1 =
b11 )
b11 >
b1000001000000110110011 .
b1000001000000110110011 @
b1000001000000110110011 F
b1000 +
b1000 H
b100 *
b100 G
b100 I
1!
#20000
0!
#25000
b11 '
b11 <
b10 (
b10 =
b100 )
b100 >
b1100010000001000110011 .
b1100010000001000110011 @
b1100010000001000110011 F
b1100 +
b1100 H
b1000 *
b1000 G
b1000 I
1!
#30000
0!
#35000
b0 &
b0 L
1:
b0 1
b0 ;
b0 C
b0 J
b1111 2
b1111 6
b1111 8
bx /
bx 4
bx A
bx '
bx <
bx (
bx =
bx 0
bx 5
bx B
bx )
bx >
bx ,
bx 3
bx ?
bx .
bx @
bx F
b10000 +
b10000 H
b1100 *
b1100 G
b1100 I
1!
#40000
0!
#45000
b10100 +
b10100 H
b10000 *
b10000 G
b10000 I
1!
#50000
0!
#55000
b11000 +
b11000 H
b10100 *
b10100 G
b10100 I
1!
#60000
0!
#65000
b11100 +
b11100 H
b11000 *
b11000 G
b11000 I
1!
#70000
0!
#75000
b100000 +
b100000 H
b11100 *
b11100 G
b11100 I
1!
#80000
0!
#85000
b100100 +
b100100 H
b100000 *
b100000 G
b100000 I
1!
#90000
0!
#95000
b101000 +
b101000 H
b100100 *
b100100 G
b100100 I
1!
#100000
0!
#105000
b101100 +
b101100 H
b101000 *
b101000 G
b101000 I
1!
#110000
0!
#115000
b110000 +
b110000 H
b101100 *
b101100 G
b101100 I
1!
#120000
0!
#125000
b110100 +
b110100 H
b110000 *
b110000 G
b110000 I
1!
#130000
0!
#135000
b111000 +
b111000 H
b110100 *
b110100 G
b110100 I
1!
#140000
0!
#145000
b111100 +
b111100 H
b111000 *
b111000 G
b111000 I
1!
#150000
0!
#155000
b1000000 +
b1000000 H
b111100 *
b111100 G
b111100 I
1!
#160000
0!
#165000
b1000100 +
b1000100 H
b1000000 *
b1000000 G
b1000000 I
1!
#170000
0!
#175000
b1001000 +
b1001000 H
b1000100 *
b1000100 G
b1000100 I
1!
#180000
0!
#185000
b1001100 +
b1001100 H
b1001000 *
b1001000 G
b1001000 I
1!
#190000
0!
#195000
b1010000 +
b1010000 H
b1001100 *
b1001100 G
b1001100 I
1!
#200000
0!
#205000
b1010100 +
b1010100 H
b1010000 *
b1010000 G
b1010000 I
1!
