week 1/decoder.v
module decoder(
    input wire [31:0] instr,
    output wire [6:0] opcode,
    output wire [4:0] rd,
    output wire [2:0] funct3,
    output wire [4:0] rs1,
    output wire [4:0] rs2,
    output wire [6:0] funct7
);
assign opcode = instr[6:0];
assign rd     = instr[11:7];
assign funct3 = instr[14:12];
assign rs1    = instr[19:15];
assign rs2    = instr[24:20];
assign funct7 = instr[31:25];
endmodule

week 1/instr_mem.v
module instr_mem(
    input wire [31:0] addr,
    output wire [31:0] instr
);
reg [31:0] mem [0:255];
initial begin
    $readmemh("program.hex", mem);
end
assign instr = mem[addr[9:2]]; // word‑aligned
endmodule

week 1/pc.v
module pc(
    input wire clk,
    input wire reset,
    input wire [31:0] pc_next,
    output reg [31:0] pc_out
);
always @(posedge clk or posedge reset) begin
    if (reset)
        pc_out <= 0;
    else
        pc_out <= pc_next;
end
endmodule

week 1/top_week2.v
module top_week2(
    input wire clk,
    input wire reset
);
wire [31:0] pc_out, pc_next, instr;
wire [6:0] opcode;
wire [4:0] rd, rs1, rs2;
wire [2:0] funct3;
wire [6:0] funct7;

assign pc_next = pc_out + 4;

pc PC(clk, reset, pc_next, pc_out);
instr_mem IM(pc_out, instr);
decoder DEC(instr, opcode, rd, funct3, rs1, rs2, funct7);
endmodule

week 2/tb_top_week2.v
module tb_top_week2;
reg clk, reset;
top_week2 uut(clk, reset);

initial begin
    $dumpfile("top_week2.vcd");
    $dumpvars(0, tb_top_week2);
    clk = 0; reset = 1;
    #10 reset = 0;
    #100 $finish;
end

always #5 clk = ~clk;
endmodule

week 2/top_week2.vcd
$date
	Sat Jun 20 14:01:06 2026
$end
$version
	Icarus Verilog
$end
$timescale
	1s
$end
$scope module tb_top_week2 $end
$var reg 1 ! clk $end
$var reg 1 " reset $end
$scope module uut $end
$var wire 1 ! clk $end
$var wire 1 " reset $end
$var wire 5 # rs2 [4:0] $end
$var wire 5 $ rs1 [4:0] $end
$var wire 5 % rd [4:0] $end
$var wire 32 & pc_out [31:0] $end
$var wire 32 ' pc_next [31:0] $end
$var wire 7 ( opcode [6:0] $end
$var wire 32 ) instr [31:0] $end
$var wire 7 * funct7 [6:0] $end
$var wire 3 + funct3 [2:0] $end
$scope module DEC $end
$var wire 5 , rs2 [4:0] $end
$var wire 5 - rs1 [4:0] $end
$var wire 5 . rd [4:0] $end
$var wire 7 / opcode [6:0] $end
$var wire 32 0 instr [31:0] $end
$var wire 7 1 funct7 [6:0] $end
$var wire 3 2 funct3 [2:0] $end
$upscope $end
$scope module IM $end
$var wire 32 3 instr [31:0] $end
$var wire 32 4 addr [31:0] $end
$upscope $end
$scope module PC $end
$var wire 1 ! clk $end
$var wire 32 5 pc_next [31:0] $end
$var wire 1 " reset $end
$var reg 32 6 pc_out [31:0] $end
$upscope $end
$upscope $end
$upscope $end
$enddefinitions $end
$comment Show the parameter values. $end
$dumpall
$end
#0
$dumpvars
b0 6
b100 5
b0 4
b110011 3
b0 2
b0 1
b110011 0
b110011 /
b0 .
b0 -
b0 ,
b0 +
b0 *
b110011 )
b110011 (
b100 '
b0 &
b0 %
b0 $
b0 #
1"
0!
$end
#5
1!
#10
0!
0"
#15
b10 #
b10 ,
b1 $
b1 -
b11 %
b11 .
b1000001000000110110011 )
b1000001000000110110011 0
b1000001000000110110011 3
b1000 '
b1000 5
b100 &
b100 4
b100 6
1!
#20
0!
#25
b11 #
b11 ,
b10 $
b10 -
b100 %
b100 .
b1100010000001000110011 )
b1100010000001000110011 0
b1100010000001000110011 3
b1100 '
b1100 5
b1000 &
b1000 4
b1000 6
1!
#30
0!
#35
bx *
bx 1
bx #
bx ,
bx $
bx -
bx +
bx 2
bx %
bx .
bx (
bx /
bx )
bx 0
bx 3
b10000 '
b10000 5
b1100 &
b1100 4
b1100 6
1!
#40
0!
#45
b10100 '
b10100 5
b10000 &
b10000 4
b10000 6
1!
#50
0!
#55
b11000 '
b11000 5
b10100 &
b10100 4
b10100 6
1!
#60
0!
#65
b11100 '
b11100 5
b11000 &
b11000 4
b11000 6
1!
#70
0!
#75
b100000 '
b100000 5
b11100 &
b11100 4
b11100 6
1!
#80
0!
#85
b100100 '
b100100 5
b100000 &
b100000 4
b100000 6
1!
#90
0!
#95
b101000 '
b101000 5
b100100 &
b100100 4
b100100 6
1!
#100
0!
#105
b101100 '
b101100 5
b101000 &
b101000 4
b101000 6
1!
